extremals/__init__.py
extremals/extremals.py
extremals/extremals_doc.py
extremals-0.2.dist-info/LICENSE
extremals-0.2.dist-info/METADATA
extremals-0.2.dist-info/WHEEL
extremals-0.2.dist-info/top_level.txt
extremals-0.2.dist-info/RECORD
