Metadata-Version: 2.1
Name: extremals
Version: 0.2
Summary: Toolset to inspect pandas dataframes looking for "extremals rows", i.e. rows "numerically different" from others.
Home-page: https://fabio-tonini.github.io/extremals/
Author: Fabio Tonini
Author-email: tonini.work@gmail.com
License: UNKNOWN
Project-URL: Bug Tracker, https://github.com/fabio-tonini/extremals/issues
Platform: UNKNOWN
Classifier: Programming Language :: Python :: 3
Classifier: License :: OSI Approved :: Apache Software License
Classifier: Operating System :: OS Independent
Requires-Python: >=3
License-File: LICENSE
